searchbhai/__init__.py
searchbhai/cli.py
searchbhai-0.1.0.dist-info/METADATA
searchbhai-0.1.0.dist-info/WHEEL
searchbhai-0.1.0.dist-info/entry_points.txt
searchbhai-0.1.0.dist-info/RECORD
